jpterm/__init__.py
jpterm/cli.py
jpterm-0.3.10.dist-info/METADATA
jpterm-0.3.10.dist-info/WHEEL
jpterm-0.3.10.dist-info/entry_points.txt
jpterm-0.3.10.dist-info/licenses/LICENSE
jpterm-0.3.10.dist-info/RECORD
