Metadata-Version: 2.4
Name: jpterm
Version: 0.3.10
Summary: Jupyter in the terminal
Project-URL: Homepage, https://github.com/davidbrochart/jpterm
Author-email: David Brochart <david.brochart@gmail.com>
License: MIT
License-File: LICENSE
Keywords: jupyter,textual
Classifier: Development Status :: 4 - Beta
Classifier: Programming Language :: Python
Classifier: Programming Language :: Python :: 3.10
Classifier: Programming Language :: Python :: 3.11
Classifier: Programming Language :: Python :: 3.12
Classifier: Programming Language :: Python :: 3.13
Classifier: Programming Language :: Python :: Implementation :: CPython
Classifier: Programming Language :: Python :: Implementation :: PyPy
Requires-Python: >=3.10
Requires-Dist: rich-click>=1.6.0
Requires-Dist: txl-cell==0.3.7
Requires-Dist: txl-console==0.3.7
Requires-Dist: txl-editors==0.3.7
Requires-Dist: txl-file-browser==0.3.7
Requires-Dist: txl-image-viewer==0.3.7
Requires-Dist: txl-jpterm==0.3.8
Requires-Dist: txl-kernel==0.3.9
Requires-Dist: txl-launcher==0.3.7
Requires-Dist: txl-local-contents==0.3.7
Requires-Dist: txl-local-kernels==0.3.7
Requires-Dist: txl-local-terminals==0.3.8
Requires-Dist: txl-markdown-viewer==0.3.7
Requires-Dist: txl-notebook-editor==0.3.7
Requires-Dist: txl-remote-contents==0.3.7
Requires-Dist: txl-remote-kernels==0.3.7
Requires-Dist: txl-remote-terminals==0.3.7
Requires-Dist: txl-terminal==0.3.7
Requires-Dist: txl-text-editor==0.3.7
Requires-Dist: txl-widgets==0.3.7
Requires-Dist: txl==0.3.3
Provides-Extra: docs
Requires-Dist: mkdocs; extra == 'docs'
Requires-Dist: mkdocs-material; extra == 'docs'
Requires-Dist: mkdocstrings-python; extra == 'docs'
